{"data": {"id": "2825_timeout_forsen_2022-08-29_apapz94", "labels": [{"anotation_id": 0, "step_1": ["Excessive & Repetitive"], "target_1": null, "step_2": ["Excessive & Repetitive"], "target_2": null, "step_3": ["Excessive & Repetitive"], "target_3": null, "comment": null, "streamer_knowledge": null, "twitch_knowledge": null}, {"anotation_id": 1, "step_1": ["Incivility"], "target_1": null, "step_2": ["Incivility"], "target_2": null, "step_3": ["HIB"], "target_3": ["Broadcaster"], "comment": ["영상속 top right은 스트리머 캠 화면"], "streamer_knowledge": null, "twitch_knowledge": null}, {"anotation_id": 2, "step_1": ["Excessive & Repetitive", "HIB"], "target_1": ["Broadcaster"], "step_2": ["Excessive & Repetitive", "HIB"], "target_2": ["Broadcaster"], "step_3": ["Excessive & Repetitive", "HIB"], "target_3": ["Broadcaster"], "comment": ["Loquacious almost always holds a negative connotation, thus making it a more precise word than talkative."], "streamer_knowledge": null, "twitch_knowledge": null}]}}
